magnumpi/__init__.py
magnumpi/makeindex.py
magnumpi/test_makeindex.py
magnum_pi-1.1.data/scripts/makeindex
magnum_pi-1.1.dist-info/pydist.json
magnum_pi-1.1.dist-info/entry_points.txt
magnum_pi-1.1.dist-info/DESCRIPTION.rst
magnum_pi-1.1.dist-info/RECORD
magnum_pi-1.1.dist-info/top_level.txt
magnum_pi-1.1.dist-info/WHEEL
magnum_pi-1.1.dist-info/METADATA
