Metadata-Version: 2.0
Name: magnum-pi
Version: 1.1
Summary: Builds a python package index out of a directory of packages
Home-page: https://github.com/ronaldevers/magnum-pi/
Author: Ronald Evers
Author-email: ronald@ch10.nl
License: MIT
Keywords: python eggs pypi index package gz tar zip whl wheel
Platform: UNKNOWN
Classifier: Intended Audience :: Developers
Classifier: Programming Language :: Python
